tenji/__init__.py
tenji/client.py
tenji/mfc_response.py
tenji/exceptions/__init__.py
tenji/exceptions/parser_exception.py
tenji/exceptions/request_exception.py
tenji/model/__init__.py
tenji/model/category.py
tenji/model/meta.py
tenji/model/paginated.py
tenji/model/item/__init__.py
tenji/model/item/item.py
tenji/model/item/partner_listing.py
tenji/model/item/partner_status.py
tenji/model/shop/__init__.py
tenji/model/shop/shop.py
tenji/model/shop/shop_category.py
tenji/model/shop/shop_list_item.py
tenji/model/user/__init__.py
tenji/model/user/collection.py
tenji/model/user/collectionstatus.py
tenji/model/user/profile.py
tenji/model/user/user_list.py
tenji/model/user/user_list_item.py
tenji/model/user/users_lists.py
tenji/parser/__init__.py
tenji/parser/home.py
tenji/parser/parser_base.py
tenji/parser/item/__init__.py
tenji/parser/item/item.py
tenji/parser/item/partner_listing.py
tenji/parser/shop/__init__.py
tenji/parser/shop/shop.py
tenji/parser/shop/shops.py
tenji/parser/user/__init__.py
tenji/parser/user/collection.py
tenji/parser/user/profile.py
tenji/parser/user/user_list.py
tenji/parser/user/user_lists.py
tenji/request/__init__.py
tenji/request/home.py
tenji/request/login.py
tenji/request/request_base.py
tenji/request/item/__init__.py
tenji/request/item/buy.py
tenji/request/item/item.py
tenji/request/shop/__init__.py
tenji/request/shop/shop.py
tenji/request/shop/shops.py
tenji/request/user/__init__.py
tenji/request/user/collection.py
tenji/request/user/profile.py
tenji/request/user/user_list.py
tenji/request/user/users_lists.py
tenji-0.2.dist-info/LICENSE
tenji-0.2.dist-info/METADATA
tenji-0.2.dist-info/WHEEL
tenji-0.2.dist-info/top_level.txt
tenji-0.2.dist-info/RECORD
