Metadata-Version: 2.1
Name: tenji
Version: 0.2
Summary: Asyncronous Python client for scraping data from MyFigureCollection (MFC).
Author-email: Nate Shoffner <nate.shoffner@gmail.com>
Project-URL: Homepage, https://github.com/Tenji-hin/tenji
Project-URL: Bug Tracker, https://github.com/Tenji-hin/tenji/issues
Keywords: myfigurecollection,mfc,parser,scraper
Classifier: Programming Language :: Python :: 3
Classifier: License :: OSI Approved :: MIT License
Classifier: Operating System :: OS Independent
Requires-Python: >=3.9
License-File: LICENSE
Requires-Dist: aiohttp
Requires-Dist: beautifulsoup4
Requires-Dist: pydantic
